pysvm/__init__.py
pysvm/rff.py
pysvm/solver.py
pysvm/svm/__init__.py
pysvm/svm/oc_svm.py
pysvm/svm/svc.py
pysvm/svm/svr.py
pysvm-0.2.dist-info/LICENSE
pysvm-0.2.dist-info/METADATA
pysvm-0.2.dist-info/WHEEL
pysvm-0.2.dist-info/top_level.txt
pysvm-0.2.dist-info/RECORD
