Metadata-Version: 2.1
Name: pysvm
Version: 0.2
Summary: PySVM : A NumPy implementation of SVM based on SMO algorithm
Home-page: https://github.com/Kaslanarian/PySVM
Author: Welt
Author-email: xingcy@smail.nju.edu.cn
Maintainer: Welt
Maintainer-email: xingcy@smail.nju.edu.cn
License: MIT License
License-File: LICENSE
Requires-Dist: numpy
Requires-Dist: sklearn
